<?xml version="1.0" encoding="utf-8"?>
<PaFields version="2.1">
	<Field Name="Phonetic">
		<Font Name="Doulos SIL" Size="13" Bold="false" Italic="false" />
		<CanBeInterlinear>true</CanBeInterlinear>
		<IsParsed>true</IsParsed>
		<IsPhonetic>true</IsPhonetic>
		<IsReference>false</IsReference>
		<IsCVPattern>false</IsCVPattern>
		<IsDate>false</IsDate>
		<FwQueryFieldName>phonetic</FwQueryFieldName>
		<IsAudioFile>false</IsAudioFile>
		<IsAudioOffset>false</IsAudioOffset>
		<IsAudioLength>false</IsAudioLength>
		<VisibleInGrid>true</VisibleInGrid>
		<VisibleInRecView>true</VisibleInRecView>
		<DisplayIndexInGrid>0</DisplayIndexInGrid>
		<DisplayIndexInRecView>0</DisplayIndexInRecView>
		<FwWritingSystemType>Vernacular</FwWritingSystemType>
	</Field>
	<Field Name="Phonemic">
		<Font Name="Doulos SIL" Size="13" Bold="false" Italic="false" />
		<CanBeInterlinear>true</CanBeInterlinear>
		<IsParsed>true</IsParsed>
		<IsPhonetic>false</IsPhonetic>
		<IsPhonemic>true</IsPhonemic>
		<IsReference>false</IsReference>
		<IsCVPattern>false</IsCVPattern>
		<IsDate>false</IsDate>
		<FwQueryFieldName>phonemic</FwQueryFieldName>
		<IsAudioFile>false</IsAudioFile>
		<IsAudioOffset>false</IsAudioOffset>
		<IsAudioLength>false</IsAudioLength>
		<VisibleInGrid>false</VisibleInGrid>
		<VisibleInRecView>true</VisibleInRecView>
		<DisplayIndexInGrid>1</DisplayIndexInGrid>
		<DisplayIndexInRecView>1</DisplayIndexInRecView>
		<FwWritingSystemType>Vernacular</FwWritingSystemType>
	</Field>
	<Field Name="Tone">
		<Font Name="Doulos SIL" Size="13" Bold="false" Italic="false" />
		<CanBeInterlinear>true</CanBeInterlinear>
		<IsParsed>true</IsParsed>
		<IsPhonetic>false</IsPhonetic>
		<IsTone>true</IsTone>
		<IsReference>false</IsReference>
		<IsCVPattern>false</IsCVPattern>
		<IsDate>false</IsDate>
		<FwQueryFieldName>tone</FwQueryFieldName>
		<IsAudioFile>false</IsAudioFile>
		<IsAudioOffset>false</IsAudioOffset>
		<IsAudioLength>false</IsAudioLength>
		<VisibleInGrid>false</VisibleInGrid>
		<VisibleInRecView>true</VisibleInRecView>
		<DisplayIndexInGrid>2</DisplayIndexInGrid>
		<DisplayIndexInRecView>2</DisplayIndexInRecView>
	</Field>
	<Field Name="Gloss">
		<CanBeInterlinear>true</CanBeInterlinear>
		<IsParsed>true</IsParsed>
		<IsPhonetic>false</IsPhonetic>
		<IsGloss>true</IsGloss>
		<IsReference>false</IsReference>
		<IsCVPattern>false</IsCVPattern>
		<IsDate>false</IsDate>
		<FwQueryFieldName>gloss1</FwQueryFieldName>
		<IsAudioFile>false</IsAudioFile>
		<IsAudioOffset>false</IsAudioOffset>
		<IsAudioLength>false</IsAudioLength>
		<VisibleInGrid>true</VisibleInGrid>
		<VisibleInRecView>true</VisibleInRecView>
		<DisplayIndexInGrid>3</DisplayIndexInGrid>
		<DisplayIndexInRecView>3</DisplayIndexInRecView>
		<FwWritingSystemType>Analysis</FwWritingSystemType>
	</Field>
	<Field Name="GlossOther1">
		<CanBeInterlinear>true</CanBeInterlinear>
		<IsParsed>true</IsParsed>
		<IsPhonetic>false</IsPhonetic>
		<IsReference>false</IsReference>
		<IsCVPattern>false</IsCVPattern>
		<IsDate>false</IsDate>
		<FwQueryFieldName>gloss2</FwQueryFieldName>
		<IsAudioFile>false</IsAudioFile>
		<IsAudioOffset>false</IsAudioOffset>
		<IsAudioLength>false</IsAudioLength>
		<VisibleInGrid>false</VisibleInGrid>
		<VisibleInRecView>true</VisibleInRecView>
		<DisplayIndexInGrid>4</DisplayIndexInGrid>
		<DisplayIndexInRecView>4</DisplayIndexInRecView>
		<FwWritingSystemType>Analysis</FwWritingSystemType>
	</Field>
	<Field Name="GlossOther2">
		<CanBeInterlinear>true</CanBeInterlinear>
		<IsParsed>true</IsParsed>
		<IsPhonetic>false</IsPhonetic>
		<IsReference>false</IsReference>
		<IsCVPattern>false</IsCVPattern>
		<IsDate>false</IsDate>
		<FwQueryFieldName>gloss3</FwQueryFieldName>
		<IsAudioFile>false</IsAudioFile>
		<IsAudioOffset>false</IsAudioOffset>
		<IsAudioLength>false</IsAudioLength>
		<VisibleInGrid>false</VisibleInGrid>
		<VisibleInRecView>true</VisibleInRecView>
		<DisplayIndexInGrid>5</DisplayIndexInGrid>
		<DisplayIndexInRecView>5</DisplayIndexInRecView>
		<FwWritingSystemType>Analysis</FwWritingSystemType>
	</Field>
	<Field Name="Ortho">
		<CanBeInterlinear>true</CanBeInterlinear>
		<IsParsed>true</IsParsed>
		<IsPhonetic>false</IsPhonetic>
		<IsOrtho>true</IsOrtho>
		<IsReference>false</IsReference>
		<IsCVPattern>false</IsCVPattern>
		<IsDate>false</IsDate>
		<FwQueryFieldName>ortho</FwQueryFieldName>
		<IsAudioFile>false</IsAudioFile>
		<IsAudioOffset>false</IsAudioOffset>
		<IsAudioLength>false</IsAudioLength>
		<VisibleInGrid>false</VisibleInGrid>
		<VisibleInRecView>true</VisibleInRecView>
		<DisplayIndexInGrid>6</DisplayIndexInGrid>
		<DisplayIndexInRecView>6</DisplayIndexInRecView>
		<FwWritingSystemType>Vernacular</FwWritingSystemType>
	</Field>
	<Field Name="POS">
		<CanBeInterlinear>true</CanBeInterlinear>
		<IsParsed>true</IsParsed>
		<IsPhonetic>false</IsPhonetic>
		<IsReference>false</IsReference>
		<IsCVPattern>false</IsCVPattern>
		<IsDate>false</IsDate>
		<FwQueryFieldName>pos</FwQueryFieldName>
		<IsAudioFile>false</IsAudioFile>
		<IsAudioOffset>false</IsAudioOffset>
		<IsAudioLength>false</IsAudioLength>
		<VisibleInGrid>true</VisibleInGrid>
		<VisibleInRecView>true</VisibleInRecView>
		<DisplayIndexInGrid>7</DisplayIndexInGrid>
		<DisplayIndexInRecView>7</DisplayIndexInRecView>
		<FwWritingSystemType>Analysis</FwWritingSystemType>
	</Field>
	<Field Name="CVPattern">
		<Font Name="Doulos SIL" Size="13" Bold="false" Italic="false" />
		<CanBeInterlinear>true</CanBeInterlinear>
		<IsParsed>true</IsParsed>
		<IsPhonetic>false</IsPhonetic>
		<IsReference>false</IsReference>
		<IsCVPattern>true</IsCVPattern>
		<FwQueryFieldName>cvpattern</FwQueryFieldName>
		<IsDate>false</IsDate>
		<IsAudioFile>false</IsAudioFile>
		<IsAudioOffset>false</IsAudioOffset>
		<IsAudioLength>false</IsAudioLength>
		<VisibleInGrid>false</VisibleInGrid>
		<VisibleInRecView>true</VisibleInRecView>
		<DisplayIndexInGrid>8</DisplayIndexInGrid>
		<DisplayIndexInRecView>8</DisplayIndexInRecView>
	</Field>
	<Field Name="Freeform">
		<CanBeInterlinear>false</CanBeInterlinear>
		<IsParsed>false</IsParsed>
		<IsPhonetic>false</IsPhonetic>
		<IsReference>false</IsReference>
		<IsCVPattern>false</IsCVPattern>
		<IsDate>false</IsDate>
		<IsAudioFile>false</IsAudioFile>
		<IsAudioOffset>false</IsAudioOffset>
		<IsAudioLength>false</IsAudioLength>
		<SaFieldName>FreeFormTranslation</SaFieldName>
		<VisibleInGrid>false</VisibleInGrid>
		<VisibleInRecView>true</VisibleInRecView>
		<DisplayIndexInGrid>9</DisplayIndexInGrid>
		<DisplayIndexInRecView>9</DisplayIndexInRecView>
	</Field>
	<Field Name="Reference">
		<CanBeInterlinear>false</CanBeInterlinear>
		<IsParsed>false</IsParsed>
		<IsPhonetic>false</IsPhonetic>
		<IsReference>true</IsReference>
		<IsCVPattern>false</IsCVPattern>
		<IsDate>false</IsDate>
		<FwQueryFieldName>ref</FwQueryFieldName>
		<IsAudioFile>false</IsAudioFile>
		<IsAudioOffset>false</IsAudioOffset>
		<IsAudioLength>false</IsAudioLength>
		<VisibleInGrid>true</VisibleInGrid>
		<VisibleInRecView>true</VisibleInRecView>
		<DisplayIndexInGrid>10</DisplayIndexInGrid>
		<DisplayIndexInRecView>10</DisplayIndexInRecView>
	</Field>
	<Field Name="NotebookRef">
		<CanBeInterlinear>false</CanBeInterlinear>
		<IsParsed>false</IsParsed>
		<IsPhonetic>false</IsPhonetic>
		<IsReference>false</IsReference>
		<IsCVPattern>false</IsCVPattern>
		<IsDate>false</IsDate>
		<IsAudioFile>false</IsAudioFile>
		<IsAudioOffset>false</IsAudioOffset>
		<IsAudioLength>false</IsAudioLength>
		<SaFieldName>NoteBookReference</SaFieldName>
		<VisibleInGrid>false</VisibleInGrid>
		<VisibleInRecView>true</VisibleInRecView>
		<DisplayIndexInGrid>11</DisplayIndexInGrid>
		<DisplayIndexInRecView>11</DisplayIndexInRecView>
	</Field>
	<Field Name="Dialect">
		<CanBeInterlinear>false</CanBeInterlinear>
		<IsParsed>false</IsParsed>
		<IsPhonetic>false</IsPhonetic>
		<IsReference>false</IsReference>
		<IsCVPattern>false</IsCVPattern>
		<IsDate>false</IsDate>
		<IsAudioFile>false</IsAudioFile>
		<IsAudioOffset>false</IsAudioOffset>
		<IsAudioLength>false</IsAudioLength>
		<SaFieldName>Dialect</SaFieldName>
		<VisibleInGrid>false</VisibleInGrid>
		<VisibleInRecView>true</VisibleInRecView>
		<DisplayIndexInGrid>12</DisplayIndexInGrid>
		<DisplayIndexInRecView>12</DisplayIndexInRecView>
	</Field>
	<Field Name="EthnologueId">
		<CanBeInterlinear>false</CanBeInterlinear>
		<IsParsed>false</IsParsed>
		<IsPhonetic>false</IsPhonetic>
		<IsReference>false</IsReference>
		<IsCVPattern>false</IsCVPattern>
		<IsDate>false</IsDate>
		<IsAudioFile>false</IsAudioFile>
		<IsAudioOffset>false</IsAudioOffset>
		<IsAudioLength>false</IsAudioLength>
		<SaFieldName>EthnologueId</SaFieldName>
		<VisibleInGrid>false</VisibleInGrid>
		<VisibleInRecView>true</VisibleInRecView>
		<DisplayIndexInGrid>13</DisplayIndexInGrid>
		<DisplayIndexInRecView>13</DisplayIndexInRecView>
	</Field>
	<Field Name="LanguageName">
		<CanBeInterlinear>false</CanBeInterlinear>
		<IsParsed>false</IsParsed>
		<IsPhonetic>false</IsPhonetic>
		<IsReference>false</IsReference>
		<IsCVPattern>false</IsCVPattern>
		<IsDate>false</IsDate>
		<IsAudioFile>false</IsAudioFile>
		<IsAudioOffset>false</IsAudioOffset>
		<IsAudioLength>false</IsAudioLength>
		<SaFieldName>LanguageName</SaFieldName>
		<VisibleInGrid>false</VisibleInGrid>
		<VisibleInRecView>true</VisibleInRecView>
		<DisplayIndexInGrid>14</DisplayIndexInGrid>
		<DisplayIndexInRecView>14</DisplayIndexInRecView>
	</Field>
	<Field Name="Region">
		<CanBeInterlinear>false</CanBeInterlinear>
		<IsParsed>false</IsParsed>
		<IsPhonetic>false</IsPhonetic>
		<IsReference>false</IsReference>
		<IsCVPattern>false</IsCVPattern>
		<IsDate>false</IsDate>
		<IsAudioFile>false</IsAudioFile>
		<IsAudioOffset>false</IsAudioOffset>
		<IsAudioLength>false</IsAudioLength>
		<SaFieldName>Region</SaFieldName>
		<VisibleInGrid>false</VisibleInGrid>
		<VisibleInRecView>true</VisibleInRecView>
		<DisplayIndexInGrid>15</DisplayIndexInGrid>
		<DisplayIndexInRecView>15</DisplayIndexInRecView>
	</Field>
	<Field Name="Country">
		<CanBeInterlinear>false</CanBeInterlinear>
		<IsParsed>false</IsParsed>
		<IsPhonetic>false</IsPhonetic>
		<IsReference>false</IsReference>
		<IsCVPattern>false</IsCVPattern>
		<IsDate>false</IsDate>
		<IsAudioFile>false</IsAudioFile>
		<IsAudioOffset>false</IsAudioOffset>
		<IsAudioLength>false</IsAudioLength>
		<SaFieldName>Country</SaFieldName>
		<VisibleInGrid>false</VisibleInGrid>
		<VisibleInRecView>true</VisibleInRecView>
		<DisplayIndexInGrid>16</DisplayIndexInGrid>
		<DisplayIndexInRecView>16</DisplayIndexInRecView>
	</Field>
	<Field Name="Family">
		<CanBeInterlinear>false</CanBeInterlinear>
		<IsParsed>false</IsParsed>
		<IsPhonetic>false</IsPhonetic>
		<IsReference>false</IsReference>
		<IsCVPattern>false</IsCVPattern>
		<IsDate>false</IsDate>
		<IsAudioFile>false</IsAudioFile>
		<IsAudioOffset>false</IsAudioOffset>
		<IsAudioLength>false</IsAudioLength>
		<SaFieldName>Family</SaFieldName>
		<VisibleInGrid>false</VisibleInGrid>
		<VisibleInRecView>true</VisibleInRecView>
		<DisplayIndexInGrid>17</DisplayIndexInGrid>
		<DisplayIndexInRecView>17</DisplayIndexInRecView>
	</Field>
	<Field Name="Transcriber">
		<CanBeInterlinear>false</CanBeInterlinear>
		<IsParsed>false</IsParsed>
		<IsPhonetic>false</IsPhonetic>
		<IsReference>false</IsReference>
		<IsCVPattern>false</IsCVPattern>
		<IsDate>false</IsDate>
		<IsAudioFile>false</IsAudioFile>
		<IsAudioOffset>false</IsAudioOffset>
		<IsAudioLength>false</IsAudioLength>
		<SaFieldName>Transcriber</SaFieldName>
		<VisibleInGrid>false</VisibleInGrid>
		<VisibleInRecView>true</VisibleInRecView>
		<DisplayIndexInGrid>18</DisplayIndexInGrid>
		<DisplayIndexInRecView>18</DisplayIndexInRecView>
		<FwQueryFieldName>transcriber</FwQueryFieldName>
	</Field>
	<Field Name="SpeakerName">
		<CanBeInterlinear>false</CanBeInterlinear>
		<IsParsed>false</IsParsed>
		<IsPhonetic>false</IsPhonetic>
		<IsReference>false</IsReference>
		<IsCVPattern>false</IsCVPattern>
		<IsDate>false</IsDate>
		<IsAudioFile>false</IsAudioFile>
		<IsAudioOffset>false</IsAudioOffset>
		<IsAudioLength>false</IsAudioLength>
		<SaFieldName>SpeakerName</SaFieldName>
		<VisibleInGrid>false</VisibleInGrid>
		<VisibleInRecView>true</VisibleInRecView>
		<DisplayIndexInGrid>19</DisplayIndexInGrid>
		<DisplayIndexInRecView>19</DisplayIndexInRecView>
		<FwQueryFieldName>spkr</FwQueryFieldName>
	</Field>
	<Field Name="SpeakerGender">
		<CanBeInterlinear>false</CanBeInterlinear>
		<IsParsed>false</IsParsed>
		<IsPhonetic>false</IsPhonetic>
		<IsReference>false</IsReference>
		<IsCVPattern>false</IsCVPattern>
		<IsDate>false</IsDate>
		<IsAudioFile>false</IsAudioFile>
		<IsAudioOffset>false</IsAudioOffset>
		<IsAudioLength>false</IsAudioLength>
		<SaFieldName>SpeakerGender</SaFieldName>
		<VisibleInGrid>false</VisibleInGrid>
		<VisibleInRecView>true</VisibleInRecView>
		<DisplayIndexInGrid>20</DisplayIndexInGrid>
		<DisplayIndexInRecView>20</DisplayIndexInRecView>
	</Field>
	<Field Name="Comment">
		<CanBeInterlinear>false</CanBeInterlinear>
		<IsParsed>false</IsParsed>
		<IsPhonetic>false</IsPhonetic>
		<IsReference>false</IsReference>
		<IsCVPattern>false</IsCVPattern>
		<IsDate>false</IsDate>
		<IsAudioFile>false</IsAudioFile>
		<IsAudioOffset>false</IsAudioOffset>
		<IsAudioLength>false</IsAudioLength>
		<VisibleInGrid>false</VisibleInGrid>
		<VisibleInRecView>true</VisibleInRecView>
		<DisplayIndexInGrid>21</DisplayIndexInGrid>
		<DisplayIndexInRecView>21</DisplayIndexInRecView>
		<FwQueryFieldName>comment</FwQueryFieldName>
	</Field>
	<Field Name="Date">
		<CanBeInterlinear>false</CanBeInterlinear>
		<IsParsed>false</IsParsed>
		<IsPhonetic>false</IsPhonetic>
		<IsReference>false</IsReference>
		<IsCVPattern>false</IsCVPattern>
		<IsDate>true</IsDate>
		<IsAudioFile>false</IsAudioFile>
		<IsAudioOffset>false</IsAudioOffset>
		<IsAudioLength>false</IsAudioLength>
		<VisibleInGrid>false</VisibleInGrid>
		<VisibleInRecView>true</VisibleInRecView>
		<DisplayIndexInGrid>22</DisplayIndexInGrid>
		<DisplayIndexInRecView>22</DisplayIndexInRecView>
	</Field>
	<Field Name="DataSource">
		<CanBeInterlinear>false</CanBeInterlinear>
		<IsParsed>false</IsParsed>
		<IsPhonetic>false</IsPhonetic>
		<IsReference>false</IsReference>
		<IsCVPattern>false</IsCVPattern>
		<IsDate>false</IsDate>
		<IsDataSource>true</IsDataSource>
		<IsAudioFile>false</IsAudioFile>
		<IsAudioOffset>false</IsAudioOffset>
		<IsAudioLength>false</IsAudioLength>
		<VisibleInGrid>false</VisibleInGrid>
		<VisibleInRecView>false</VisibleInRecView>
		<DisplayIndexInGrid>23</DisplayIndexInGrid>
		<DisplayIndexInRecView>23</DisplayIndexInRecView>
	</Field>
	<Field Name="DataSourcePath">
		<CanBeInterlinear>false</CanBeInterlinear>
		<IsParsed>false</IsParsed>
		<IsPhonetic>false</IsPhonetic>
		<IsReference>false</IsReference>
		<IsCVPattern>false</IsCVPattern>
		<IsDate>false</IsDate>
		<IsDataSourcePath>true</IsDataSourcePath>
		<IsAudioFile>false</IsAudioFile>
		<IsAudioOffset>false</IsAudioOffset>
		<IsAudioLength>false</IsAudioLength>
		<VisibleInGrid>false</VisibleInGrid>
		<VisibleInRecView>false</VisibleInRecView>
		<DisplayIndexInGrid>24</DisplayIndexInGrid>
		<DisplayIndexInRecView>24</DisplayIndexInRecView>
	</Field>
	<Field Name="AudioFile">
		<CanBeInterlinear>false</CanBeInterlinear>
		<IsParsed>false</IsParsed>
		<IsPhonetic>false</IsPhonetic>
		<IsReference>false</IsReference>
		<IsCVPattern>false</IsCVPattern>
		<IsDate>false</IsDate>
		<FwQueryFieldName>audiofile</FwQueryFieldName>
		<IsAudioFile>true</IsAudioFile>
		<IsAudioOffset>false</IsAudioOffset>
		<IsAudioLength>false</IsAudioLength>
		<VisibleInGrid>false</VisibleInGrid>
		<VisibleInRecView>true</VisibleInRecView>
		<DisplayIndexInGrid>25</DisplayIndexInGrid>
		<DisplayIndexInRecView>25</DisplayIndexInRecView>
	</Field>
	<Field Name="AudioOffset">
		<CanBeInterlinear>false</CanBeInterlinear>
		<IsParsed>true</IsParsed>
		<IsPhonetic>false</IsPhonetic>
		<IsReference>false</IsReference>
		<IsCVPattern>false</IsCVPattern>
		<IsDate>false</IsDate>
		<IsAudioFile>false</IsAudioFile>
		<IsAudioOffset>true</IsAudioOffset>
		<IsAudioLength>false</IsAudioLength>
		<VisibleInGrid>false</VisibleInGrid>
		<VisibleInRecView>false</VisibleInRecView>
	</Field>
	<Field Name="AudioLength">
		<CanBeInterlinear>false</CanBeInterlinear>
		<IsParsed>true</IsParsed>
		<IsPhonetic>false</IsPhonetic>
		<IsReference>false</IsReference>
		<IsCVPattern>false</IsCVPattern>
		<IsDate>false</IsDate>
		<IsAudioFile>false</IsAudioFile>
		<IsAudioOffset>false</IsAudioOffset>
		<IsAudioLength>true</IsAudioLength>
		<VisibleInGrid>false</VisibleInGrid>
		<VisibleInRecView>false</VisibleInRecView>
	</Field>
	<Field Name="GUID">
		<CanBeInterlinear>false</CanBeInterlinear>
		<FwQueryFieldName>guid</FwQueryFieldName>
		<IsParsed>false</IsParsed>
		<IsPhonetic>false</IsPhonetic>
		<IsReference>false</IsReference>
		<IsCVPattern>false</IsCVPattern>
		<IsDate>false</IsDate>
		<IsGuid>true</IsGuid>
		<IsAudioFile>false</IsAudioFile>
		<IsAudioOffset>false</IsAudioOffset>
		<IsAudioLength>false</IsAudioLength>
		<VisibleInGrid>false</VisibleInGrid>
		<VisibleInRecView>false</VisibleInRecView>
	</Field>
</PaFields>